.gitignore
ArtisticLicense20.html
README
README.md
callDocSphinx.sh
licenses-amendments.txt
setup.cfg
setup.py
UseCases/.gitignore
UseCases/CallCase.py
UseCases/README
UseCases/README.md
UseCases/__init__.py
UseCases/myscript.sh
UseCases/remote_debug/__init__.py
UseCases/remote_debug/defaults/CallCase.py
UseCases/remote_debug/defaults/__init__.py
UseCases/remote_debug/find_pydevd/__init__.py
UseCases/remote_debug/find_pydevd/1_rootforscan/CallCase.py
UseCases/remote_debug/find_pydevd/1_rootforscan/__init__.py
UseCases/remote_debug/find_pydevd/2_PYDEVDSCAN/CallCase.py
UseCases/remote_debug/find_pydevd/2_PYDEVDSCAN/__init__.py
UseCases/remote_debug/find_pydevd/3_sys_path/CallCase.py
UseCases/remote_debug/find_pydevd/3_sys_path/__init__.py
UseCases/remote_debug/find_pydevd/4_HOME_eclipse/__init__.py
UseCases/remote_debug/find_pydevd/5_installed_as_dropin/__init__.py
UseCases/remote_debug/get_rdbg_options/__init__.py
UseCases/remote_debug/get_rdbg_options/rdbgroot/CallCase.py
UseCases/remote_debug/get_rdbg_options/rdbgroot/__init__.py
UseCases/remote_debug/get_rdbg_options/rdbgsub/CallCase.py
UseCases/remote_debug/get_rdbg_options/rdbgsub/__init__.py
UseCases/selftest/__init__.py
UseCases/selftest/epyunit/__init__.py
UseCases/selftest/epyunit/myscript.sh
UseCases/selftest/epyunit/bash/CallCase.py
UseCases/selftest/epyunit/bash/__init__.py
UseCases/selftest/epyunit/default/CallCase.py
UseCases/selftest/epyunit/default/__init__.py
UseCases/selftest/epyunit/perl/CallCase.py
UseCases/selftest/epyunit/perl/__init__.py
UseCases/selftest/epyunit/python/CallCase.py
UseCases/selftest/epyunit/python/__init__.py
UseCases/test_simulators/__init__.py
UseCases/test_simulators/myscript/__init__.py
UseCases/test_simulators/myscript/bash/__init__.py
UseCases/test_simulators/myscript/bash/exit_ignore/CallCase.py
UseCases/test_simulators/myscript/bash/exit_ignore/__init__.py
UseCases/test_simulators/myscript/bash/exit_nok/CallCase.py
epyunit.egg-info/PKG-INFO
epyunit.egg-info/SOURCES.txt
epyunit.egg-info/dependency_links.txt
epyunit.egg-info/requires.txt
epyunit.egg-info/top_level.txt
