Metadata-Version: 1.1
Name: epyunit
Version: 0.2.12
Summary: The 'epyunit' package provides a wrapper for unit tests of commandline interfaces, and the automation of debugging with PyDev for external processes. The package could be used either from the comandline, or integrated into Eclipse with PyDev.
Home-page: https://sourceforge.net/projects/epyunit/
Author: Arno-Can Uestuensoez
Author-email: acue_sf2@sourceforge.net
License: Artistic-License-2.0 + Forced-Fairplay-Constraints
Download-URL: https://sourceforge.net/projects/epyunit/files/
Keywords: Python PyUnit PyDev Eclipse CLI command line test unit unittest regression regressiontest fileobjects commandline debug pydevd.py automation remote debug cross-process
Platform: any
Classifier: Development Status :: 3 - Alpha
Classifier: Intended Audience :: Developers
Classifier: License :: Free To Use But Restricted
Classifier: License :: OSI Approved :: Artistic License
Classifier: Natural Language :: English
Classifier: Operating System :: Microsoft :: Windows :: Windows 7
Classifier: Operating System :: OS Independent
Classifier: Operating System :: POSIX :: BSD :: OpenBSD
Classifier: Operating System :: POSIX :: Linux
Classifier: Operating System :: POSIX
Classifier: Operating System :: MacOS :: MacOS X
Classifier: Programming Language :: Python
Classifier: Programming Language :: Python :: 2
Classifier: Programming Language :: Python :: 2.6
Classifier: Programming Language :: Python :: 2.7
Classifier: Programming Language :: Unix Shell
Classifier: Topic :: Software Development :: Libraries :: Python Modules
Classifier: Topic :: Utilities
